easy_knowledge_retriever/__init__.py
easy_knowledge_retriever/constants.py
easy_knowledge_retriever/retriever.py
easy_knowledge_retriever/kg/__init__.py
easy_knowledge_retriever/kg/base.py
easy_knowledge_retriever/kg/concurrency.py
easy_knowledge_retriever/kg/exceptions.py
easy_knowledge_retriever/kg/namespace.py
easy_knowledge_retriever/kg/postgres_database.py
easy_knowledge_retriever/kg/registry.py
easy_knowledge_retriever/kg/services.py
easy_knowledge_retriever/kg/shared_memory.py
easy_knowledge_retriever/kg/shared_storage.py
easy_knowledge_retriever/kg/state.py
easy_knowledge_retriever/kg/types.py
easy_knowledge_retriever/kg/utils.py
easy_knowledge_retriever/kg/graph_storage/__init__.py
easy_knowledge_retriever/kg/graph_storage/base.py
easy_knowledge_retriever/kg/graph_storage/neo4j_impl.py
easy_knowledge_retriever/kg/graph_storage/networkx_impl.py
easy_knowledge_retriever/kg/graph_storage/postgres_impl.py
easy_knowledge_retriever/kg/graph_storage/utils_graph.py
easy_knowledge_retriever/kg/kv_storage/__init__.py
easy_knowledge_retriever/kg/kv_storage/base.py
easy_knowledge_retriever/kg/kv_storage/json_doc_status_impl.py
easy_knowledge_retriever/kg/kv_storage/json_kv_impl.py
easy_knowledge_retriever/kg/kv_storage/postgres_impl.py
easy_knowledge_retriever/kg/vector_storage/__init__.py
easy_knowledge_retriever/kg/vector_storage/base.py
easy_knowledge_retriever/kg/vector_storage/milvus_impl.py
easy_knowledge_retriever/kg/vector_storage/nano_vector_db_impl.py
easy_knowledge_retriever/kg/vector_storage/postgres_impl.py
easy_knowledge_retriever/llm/__init__.py
easy_knowledge_retriever/llm/client.py
easy_knowledge_retriever/llm/exceptions.py
easy_knowledge_retriever/llm/openai.py
easy_knowledge_retriever/llm/options.py
easy_knowledge_retriever/llm/prompts.py
easy_knowledge_retriever/llm/service.py
easy_knowledge_retriever/llm/types.py
easy_knowledge_retriever/llm/utils.py
easy_knowledge_retriever/operations/__init__.py
easy_knowledge_retriever/operations/chunking.py
easy_knowledge_retriever-1.2.1.dist-info/licenses/LICENSE
easy_knowledge_retriever-1.2.1.dist-info/METADATA
easy_knowledge_retriever-1.2.1.dist-info/WHEEL
easy_knowledge_retriever-1.2.1.dist-info/top_level.txt
easy_knowledge_retriever-1.2.1.dist-info/RECORD
