Metadata-Version: 2.4
Name: easy-knowledge-retriever
Version: 1.2.1
Summary: A simple and efficient RAG (Retrieval-Augmented Generation) library with Knowledge Graph support.
Author: Hankerspace
Author-email: hankerspace@gmail.com
License: CC BY-NC-SA 4.0
Classifier: Programming Language :: Python :: 3
Classifier: License :: Free for non-commercial use
Classifier: License :: Other/Proprietary License
Classifier: Operating System :: OS Independent
Requires-Python: >=3.10
License-File: LICENSE
Requires-Dist: asyncpg<1.0.0,>=0.29.0
Requires-Dist: httpx
Requires-Dist: networkx
Requires-Dist: numpy
Requires-Dist: tenacity
Requires-Dist: tiktoken
Requires-Dist: openai<3.0.0,>=2.0.0
Requires-Dist: neo4j<7.0.0,>=5.0.0
Requires-Dist: pymilvus>=2.6.2
Requires-Dist: nano-vectordb
Requires-Dist: pypdf
Requires-Dist: mineru
Requires-Dist: doclayout_yolo
Requires-Dist: ragas
Requires-Dist: datasets
Requires-Dist: ultralytics
Requires-Dist: ftfy
Requires-Dist: shapely
Requires-Dist: pyclipper
Requires-Dist: omegaconf
Requires-Dist: pypinyin
Requires-Dist: dill
Requires-Dist: langchain-openai
Requires-Dist: json_repair
Dynamic: author
Dynamic: author-email
Dynamic: classifier
Dynamic: description
Dynamic: description-content-type
Dynamic: license
Dynamic: license-file
Dynamic: requires-dist
Dynamic: requires-python
Dynamic: summary
